odoo/addons/account_debitnote/README.rst
odoo/addons/account_debitnote/__init__.py
odoo/addons/account_debitnote/__manifest__.py
odoo/addons/account_debitnote/i18n/account_debitnote.pot
odoo/addons/account_debitnote/i18n/de.po
odoo/addons/account_debitnote/i18n/es.po
odoo/addons/account_debitnote/models/__init__.py
odoo/addons/account_debitnote/models/account.py
odoo/addons/account_debitnote/models/account_invoice.py
odoo/addons/account_debitnote/models/account_move.py
odoo/addons/account_debitnote/models/ir_sequence.py
odoo/addons/account_debitnote/readme/CONFIGURE.rst
odoo/addons/account_debitnote/readme/CONTRIBUTORS.rst
odoo/addons/account_debitnote/readme/DESCRIPTION.rst
odoo/addons/account_debitnote/readme/USAGE.rst
odoo/addons/account_debitnote/static/description/icon.png
odoo/addons/account_debitnote/static/description/index.html
odoo/addons/account_debitnote/tests/__init__.py
odoo/addons/account_debitnote/tests/test_account_debitnote.py
odoo/addons/account_debitnote/views/account_invoice_view.xml
odoo/addons/account_debitnote/views/account_view.xml
odoo/addons/account_debitnote/wizard/__init__.py
odoo/addons/account_debitnote/wizard/account_invoice_debitnote.py
odoo/addons/account_debitnote/wizard/account_invoice_debitnote_view.xml
odoo12_addon_account_debitnote-12.0.1.0.0.99.dev10.dist-info/METADATA
odoo12_addon_account_debitnote-12.0.1.0.0.99.dev10.dist-info/WHEEL
odoo12_addon_account_debitnote-12.0.1.0.0.99.dev10.dist-info/top_level.txt
odoo12_addon_account_debitnote-12.0.1.0.0.99.dev10.dist-info/RECORD
